mlbstatsapi/__init__.py
mlbstatsapi/exceptions.py
mlbstatsapi/mlb_api.py
mlbstatsapi/mlb_dataadapter.py
mlbstatsapi/mlb_module.py
mlbstatsapi/models/__init__.py
mlbstatsapi/models/attendances/__init__.py
mlbstatsapi/models/attendances/attendance.py
mlbstatsapi/models/attendances/attributes.py
mlbstatsapi/models/awards/__init__.py
mlbstatsapi/models/awards/attributes.py
mlbstatsapi/models/awards/awards.py
mlbstatsapi/models/data/__init__.py
mlbstatsapi/models/data/data.py
mlbstatsapi/models/divisions/__init__.py
mlbstatsapi/models/divisions/division.py
mlbstatsapi/models/drafts/__init__.py
mlbstatsapi/models/drafts/attributes.py
mlbstatsapi/models/drafts/rounds.py
mlbstatsapi/models/game/__init__.py
mlbstatsapi/models/game/attributes.py
mlbstatsapi/models/game/game.py
mlbstatsapi/models/game/gamedata/__init__.py
mlbstatsapi/models/game/gamedata/attributes.py
mlbstatsapi/models/game/gamedata/gamedata.py
mlbstatsapi/models/game/livedata/__init__.py
mlbstatsapi/models/game/livedata/attributes.py
mlbstatsapi/models/game/livedata/livedata.py
mlbstatsapi/models/game/livedata/boxscore/__init__.py
mlbstatsapi/models/game/livedata/boxscore/attributes.py
mlbstatsapi/models/game/livedata/boxscore/boxscore.py
mlbstatsapi/models/game/livedata/linescore/__init__.py
mlbstatsapi/models/game/livedata/linescore/attributes.py
mlbstatsapi/models/game/livedata/linescore/linescore.py
mlbstatsapi/models/game/livedata/plays/__init__.py
mlbstatsapi/models/game/livedata/plays/plays.py
mlbstatsapi/models/game/livedata/plays/play/__init__.py
mlbstatsapi/models/game/livedata/plays/play/attributes.py
mlbstatsapi/models/game/livedata/plays/play/play.py
mlbstatsapi/models/game/livedata/plays/play/matchup/__init__.py
mlbstatsapi/models/game/livedata/plays/play/matchup/attributes.py
mlbstatsapi/models/game/livedata/plays/play/matchup/matchup.py
mlbstatsapi/models/game/livedata/plays/play/playevent/__init__.py
mlbstatsapi/models/game/livedata/plays/play/playevent/playevent.py
python_mlb_statsapi-0.5.25.dist-info/LICENSE
python_mlb_statsapi-0.5.25.dist-info/METADATA
python_mlb_statsapi-0.5.25.dist-info/WHEEL
python_mlb_statsapi-0.5.25.dist-info/top_level.txt
python_mlb_statsapi-0.5.25.dist-info/RECORD
