Metadata-Version: 2.1
Name: python-mlb-statsapi
Version: 0.5.25
Summary: mlbstatsapi python wrapper
Author-email: Matthew Spah <spahmatthew@gmail.com>, Kristian Nilssen <krinilssen@gmail.com>
License: Copyright (c) 2018 The Python Packaging Authority
Project-URL: Homepage, https://github.com/zero-sum-seattle/python-mlb-statsapi
Project-URL: Bug Tracker, https://github.com/zero-sum-seattle/python-mlb-statsapi/issues
Classifier: Programming Language :: Python :: 3
Classifier: License :: OSI Approved :: MIT License
Classifier: Operating System :: OS Independent
Requires-Python: >=3.10
License-File: LICENSE
Requires-Dist: requests >=2
Requires-Dist: requests-mock >=1.10.0
